README.md
setup.py
eve_cli_client/__init__.py
eve_cli_client/api_key.py
eve_cli_client/api_key_example.py
eve_cli_client/client.py
eve_cli_client.egg-info/PKG-INFO
eve_cli_client.egg-info/SOURCES.txt
eve_cli_client.egg-info/dependency_links.txt
eve_cli_client.egg-info/requires.txt
eve_cli_client.egg-info/top_level.txt