Metadata-Version: 1.0
Name: eve-cli-client
Version: 0.0.1b1
Summary: A basic cli client for testing eve-assistant without entering an API key.
Home-page: UNKNOWN
Author: Karl Voss
Author-email: karl.p.voss@gmail.com
License: MIT
Platform: UNKNOWN
